{"_type":"export","__export_format":4,"__export_date":"2021-10-22T10:21:32.785Z","__export_source":"insomnia.desktop.app:v2021.5.3","resources":[{"_id":"req_ae030469e13b41b19de8c9d52eebf7c6","parentId":"wrk_8c37dc0663da47a2b5f49cff7ef55002","modified":1634894131471,"created":1634802091600,"url":"https://localhost:44301/api/facturas","name":"Facturas","description":"","method":"GET","body":{},"parameters":[],"headers":[],"authentication":{},"metaSortKey":-1634802091600,"isPrivate":false,"settingStoreCookies":true,"settingSendCookies":true,"settingDisableRenderRequestBody":false,"settingEncodeUrl":true,"settingRebuildPath":true,"settingFollowRedirects":"global","_type":"request"},{"_id":"wrk_8c37dc0663da47a2b5f49cff7ef55002","parentId":null,"modified":1634545928503,"created":1634545928503,"name":"MF0966","description":"","scope":"collection","_type":"workspace"},{"_id":"req_599bf91a67344b6fac351af706ca6cd2","parentId":"wrk_8c37dc0663da47a2b5f49cff7ef55002","modified":1634892069342,"created":1634888965028,"url":"https://localhost:44301/api/facturas","name":"Facturas","description":"","method":"POST","body":{"mimeType":"application/json","text":"{\n\t\"Numero\": \"2021021\",\n\t\"Fecha\": \"2021-09-09T00:00:00\",\n\t\"ClienteId\": 1,\n\t\"FacturasProductos\": [\n\t\t{\n\t\t\t\"ProductoId\": 1,\n\t\t\t\"Cantidad\": 5\n\t\t},\n\t\t{\n\t\t\t\"ProductoId\": 2,\n\t\t\t\"Cantidad\": 3\n\t\t}\n\t]\n}\n"},"parameters":[],"headers":[{"name":"Content-Type","value":"application/json","id":"pair_169eeacd31ab475194b92f1ea2a2550a"}],"authentication":{},"metaSortKey":-1634686599150.5,"isPrivate":false,"settingStoreCookies":true,"settingSendCookies":true,"settingDisableRenderRequestBody":false,"settingEncodeUrl":true,"settingRebuildPath":true,"settingFollowRedirects":"global","_type":"request"},{"_id":"req_affaacafcb4b413fbd4f900f43932b50","parentId":"wrk_8c37dc0663da47a2b5f49cff7ef55002","modified":1634894093398,"created":1634890334644,"url":"https://localhost:44301/api/facturas/24","name":"Facturas","description":"","method":"PUT","body":{"mimeType":"application/json","text":"{\n\t\"Id\": 24,\n\t\"Numero\": \"20210019\",\n\t\"Fecha\": \"2021-09-10T00:00:00\",\n\t\"ClienteId\": 1,\n\t\"FacturasProductos\": [\n\t\t{\n\t\t\t\"FacturaId\": 24,\n\t\t\t\"ProductoId\": 8,\n\t\t\t\"Cantidad\": 5\n\t\t},\n\t\t{\n\t\t\t\"FacturaId\": 24,\n\t\t\t\"ProductoId\": 2,\n\t\t\t\"Cantidad\": 3\n\t\t},\n\t\t{\n\t\t\t\"FacturaId\": 24,\n\t\t\t\"ProductoId\": 3,\n\t\t\t\"Cantidad\": 3\n\t\t}\n\t]\n}"},"parameters":[],"headers":[{"name":"Content-Type","value":"application/json","id":"pair_169eeacd31ab475194b92f1ea2a2550a"}],"authentication":{},"metaSortKey":-1634628852925.75,"isPrivate":false,"settingStoreCookies":true,"settingSendCookies":true,"settingDisableRenderRequestBody":false,"settingEncodeUrl":true,"settingRebuildPath":true,"settingFollowRedirects":"global","_type":"request"},{"_id":"req_644cadc97cbe40db8735a763210c3450","parentId":"wrk_8c37dc0663da47a2b5f49cff7ef55002","modified":1634894427641,"created":1634890566435,"url":"https://localhost:44301/api/facturas/26","name":"Facturas","description":"","method":"DELETE","body":{},"parameters":[],"headers":[],"authentication":{},"metaSortKey":-1634599979813.375,"isPrivate":false,"settingStoreCookies":true,"settingSendCookies":true,"settingDisableRenderRequestBody":false,"settingEncodeUrl":true,"settingRebuildPath":true,"settingFollowRedirects":"global","_type":"request"},{"_id":"req_2baaafd5600d42ec8bca470668bf3eb7","parentId":"wrk_8c37dc0663da47a2b5f49cff7ef55002","modified":1634801064417,"created":1634555626406,"url":"https://localhost:44301/api/categorias","name":"Categorias","description":"","method":"GET","body":{},"parameters":[],"headers":[{"id":"pair_7167595a87014087b984ec05b00a7891","name":"accept","value":"text/html,application/xhtml+xml,application/xml;q=0.9,image/webp,image/apng,*/*;q=0.8,application/signed-exchange;v=b3;q=0.9","description":"","disabled":true}],"authentication":{},"metaSortKey":-1634545936783,"isPrivate":false,"settingStoreCookies":true,"settingSendCookies":true,"settingDisableRenderRequestBody":false,"settingEncodeUrl":true,"settingRebuildPath":true,"settingFollowRedirects":"global","_type":"request"},{"_id":"req_6a2d8cebb1094612940006f23146300d","parentId":"wrk_8c37dc0663da47a2b5f49cff7ef55002","modified":1634556318143,"created":1634555667385,"url":"https://localhost:44301/api/categorias/100","name":"Categoria","description":"","method":"GET","body":{},"parameters":[],"headers":[],"authentication":{},"metaSortKey":-1634545936758,"isPrivate":false,"settingStoreCookies":true,"settingSendCookies":true,"settingDisableRenderRequestBody":false,"settingEncodeUrl":true,"settingRebuildPath":true,"settingFollowRedirects":"global","_type":"request"},{"_id":"req_0500919a1cac49e2a7891616da8b56c9","parentId":"wrk_8c37dc0663da47a2b5f49cff7ef55002","modified":1634555799627,"created":1634555690399,"url":"https://localhost:44301/api/categorias","name":"Categoria","description":"","method":"POST","body":{"mimeType":"application/json","text":"{\n  \"Nombre\": \"NUEVAAAA\"\n}\n"},"parameters":[],"headers":[{"name":"Content-Type","value":"application/json","id":"pair_5d3c728bba374bc4915f86fa73613651"}],"authentication":{},"metaSortKey":-1634545936745.5,"isPrivate":false,"settingStoreCookies":true,"settingSendCookies":true,"settingDisableRenderRequestBody":false,"settingEncodeUrl":true,"settingRebuildPath":true,"settingFollowRedirects":"global","_type":"request"},{"_id":"req_05a39b07e7dd44cb93b912d6e2457dad","parentId":"wrk_8c37dc0663da47a2b5f49cff7ef55002","modified":1634555822251,"created":1634555781093,"url":"https://localhost:44301/api/categorias/54","name":"Categoria","description":"","method":"PUT","body":{"mimeType":"application/json","text":"{\n  \"Id\": 54,\n  \"Nombre\": \"Modificada 54\"\n}\n"},"parameters":[],"headers":[{"name":"Content-Type","value":"application/json","id":"pair_5d3c728bba374bc4915f86fa73613651"}],"authentication":{},"metaSortKey":-1634545936742.375,"isPrivate":false,"settingStoreCookies":true,"settingSendCookies":true,"settingDisableRenderRequestBody":false,"settingEncodeUrl":true,"settingRebuildPath":true,"settingFollowRedirects":"global","_type":"request"},{"_id":"req_903adc3b506045cba5c44de0a0dec263","parentId":"wrk_8c37dc0663da47a2b5f49cff7ef55002","modified":1634555729315,"created":1634555729315,"url":"https://localhost:44301/api/categorias/53","name":"Categoria","description":"","method":"DELETE","body":{},"parameters":[],"headers":[],"authentication":{},"metaSortKey":-1634545936739.25,"isPrivate":false,"settingStoreCookies":true,"settingSendCookies":true,"settingDisableRenderRequestBody":false,"settingEncodeUrl":true,"settingRebuildPath":true,"settingFollowRedirects":"global","_type":"request"},{"_id":"req_adf08c439cf844fa9ee197937ac9003d","parentId":"wrk_8c37dc0663da47a2b5f49cff7ef55002","modified":1634555124472,"created":1634545936733,"url":"https://localhost:44301/api/productos","name":"Productos","description":"","method":"GET","body":{},"parameters":[],"headers":[],"authentication":{},"metaSortKey":-1634545936733,"isPrivate":false,"settingStoreCookies":true,"settingSendCookies":true,"settingDisableRenderRequestBody":false,"settingEncodeUrl":true,"settingRebuildPath":true,"settingFollowRedirects":"global","_type":"request"},{"_id":"req_ba13ae1b3c2d459c88e34b1acebf834f","parentId":"wrk_8c37dc0663da47a2b5f49cff7ef55002","modified":1634555154868,"created":1634555137253,"url":"https://localhost:44301/api/productos?nombre=webapi","name":"Productos búsqueda por nombre","description":"","method":"GET","body":{},"parameters":[],"headers":[],"authentication":{},"metaSortKey":-1634486794179.75,"isPrivate":false,"settingStoreCookies":true,"settingSendCookies":true,"settingDisableRenderRequestBody":false,"settingEncodeUrl":true,"settingRebuildPath":true,"settingFollowRedirects":"global","_type":"request"},{"_id":"req_5b5f581e4899459aa4843dab3092e143","parentId":"wrk_8c37dc0663da47a2b5f49cff7ef55002","modified":1634549775307,"created":1634548702040,"url":"https://localhost:44301/api/productos/34","name":"Producto","description":"","method":"GET","body":{},"parameters":[],"headers":[],"authentication":{},"metaSortKey":-1634427651626.5,"isPrivate":false,"settingStoreCookies":true,"settingSendCookies":true,"settingDisableRenderRequestBody":false,"settingEncodeUrl":true,"settingRebuildPath":true,"settingFollowRedirects":"global","_type":"request"},{"_id":"req_b607dd31aacc47deb4d646f54e6d6bac","parentId":"wrk_8c37dc0663da47a2b5f49cff7ef55002","modified":1634549764328,"created":1634548735753,"url":"https://localhost:44301/api/productos","name":"Producto","description":"","method":"POST","body":{"mimeType":"application/json","text":"{\n  \"Nombre\": \"Creado Por WebAPI\",\n  \"Precio\":54.33,\n  \"CategoriaId\": 4\n}"},"parameters":[],"headers":[{"name":"Content-Type","value":"application/json","id":"pair_7c934ec4f9464a2d9e787c2240c577a5"}],"authentication":{},"metaSortKey":-1634368509073.25,"isPrivate":false,"settingStoreCookies":true,"settingSendCookies":true,"settingDisableRenderRequestBody":false,"settingEncodeUrl":true,"settingRebuildPath":true,"settingFollowRedirects":"global","_type":"request"},{"_id":"req_9b2999217e9a49698f70bdfce0dde6dd","parentId":"wrk_8c37dc0663da47a2b5f49cff7ef55002","modified":1634549734999,"created":1634549734999,"url":"https://localhost:44301/api/productos/29","name":"Producto","description":"","method":"PUT","body":{"mimeType":"application/json","text":"{\n  \"Id\": 29,\n  \"Nombre\": \"Modificado Por WebAPI\",\n  \"Precio\":54.33,\n  \"CategoriaId\": 4\n}"},"parameters":[],"headers":[{"name":"Content-Type","value":"application/json","id":"pair_7c934ec4f9464a2d9e787c2240c577a5"}],"authentication":{},"metaSortKey":-1634353723434.9375,"isPrivate":false,"settingStoreCookies":true,"settingSendCookies":true,"settingDisableRenderRequestBody":false,"settingEncodeUrl":true,"settingRebuildPath":true,"settingFollowRedirects":"global","_type":"request"},{"_id":"req_0172fd5df3f74bf49cbbf0b921d86f49","parentId":"wrk_8c37dc0663da47a2b5f49cff7ef55002","modified":1634548855342,"created":1634548855342,"url":"https://localhost:44301/api/productos/30","name":"Producto","description":"","method":"DELETE","body":{},"parameters":[],"headers":[],"authentication":{},"metaSortKey":-1634338937796.625,"isPrivate":false,"settingStoreCookies":true,"settingSendCookies":true,"settingDisableRenderRequestBody":false,"settingEncodeUrl":true,"settingRebuildPath":true,"settingFollowRedirects":"global","_type":"request"},{"_id":"env_321d3babbfbd52dd760ae2d74fa671281406d319","parentId":"wrk_8c37dc0663da47a2b5f49cff7ef55002","modified":1634545928523,"created":1634545928523,"name":"Base Environment","data":{},"dataPropertyOrder":null,"color":null,"isPrivate":false,"metaSortKey":1634545928523,"_type":"environment"},{"_id":"jar_321d3babbfbd52dd760ae2d74fa671281406d319","parentId":"wrk_8c37dc0663da47a2b5f49cff7ef55002","modified":1634545928539,"created":1634545928539,"name":"Default Jar","cookies":[],"_type":"cookie_jar"},{"_id":"spc_93d34c15fa634487abc728a5b97ec2ad","parentId":"wrk_8c37dc0663da47a2b5f49cff7ef55002","modified":1634545928508,"created":1634545928508,"fileName":"MF0966","contents":"","contentType":"yaml","_type":"api_spec"}]}